pathmagic/__init__.py
pathmagic/accessor.py
pathmagic/dir.py
pathmagic/file.py
pathmagic/formats.py
pathmagic/path.py
pathmagic-0.3.14.dist-info/LICENSE
pathmagic-0.3.14.dist-info/METADATA
pathmagic-0.3.14.dist-info/WHEEL
pathmagic-0.3.14.dist-info/top_level.txt
pathmagic-0.3.14.dist-info/RECORD
