Metadata-Version: 2.1
Name: pathmagic
Version: 0.3.14
Summary: Provides ORM path classes (File and Dir), which automatically emit file system IO operations upon having their attributes modified. File objects allow for easy content manipulation of many forms of files.
Home-page: https://github.com/matthewgdv/pathmagic
Author: Matt GdV
Author-email: matthewgdv@gmail.com
License: MIT
Platform: UNKNOWN
Classifier: Development Status :: 3 - Alpha
Classifier: Intended Audience :: Developers
Classifier: Programming Language :: Python :: 3.8
